Metadata-Version: 1.1
Name: BeaconTau
Version: 0.1.6
Summary: A package for interacting with BEACON data in python
Home-page: https://github.com/beaconTau/BeaconTau
Author: Ben Strutt
Author-email: strutt@physics.ucla.edu
License: GPL3
Platform: UNKNOWN
Classifier: Programming Language :: Python :: 3
Classifier: License :: OSI Approved :: GNU General Public License v3 (GPLv3)
Classifier: Operating System :: POSIX
